cnmv_data/__init__.py
cnmv_data/cnmv.py
cnmv_data-1.0.3.dist-info/METADATA
cnmv_data-1.0.3.dist-info/WHEEL
cnmv_data-1.0.3.dist-info/top_level.txt
cnmv_data-1.0.3.dist-info/RECORD
