Metadata-Version: 2.1
Name: cnmv-data
Version: 1.0.3
Summary: Extracción desde PDF de la cartera de inversión reportada por Fondos de Inversión a la CNMV
Home-page: https://github.com/afernandez119
Author: Antonio Fernandez Troyano
Author-email: a.fernandez.troyano@gmail.com
License: MIT
Platform: UNKNOWN
Requires-Dist: pymupdf
